roe/__init__.py
roe/cli.py
roe/commands/__init__.py
roe/commands/cmd_begin.py
roe/commands/cmd_deploy.py
roe/commands/cmd_end.py
roe/commands/cmd_list.py
roe/commands/cmd_logs.py
roe/commands/cmd_start.py
roe/commands/cmd_stop.py
roe/commands/cmd_undeploy.py
roe/commands/cmd_verify.py
roe/utilities/RoeClient.py
roe/utilities/__init__.py
roe/utilities/basic_utils.py
roe/utilities/errors.py
roe/utilities/init_utils.py
roe/utilities/loader.py
roe/utilities/running_utils.py
tests/__init__.py
tests/test_api_client.py
tests/test_begin.py
tests/test_deploy.py
tests/test_end.py
tests/test_list.py
tests/test_logs.py
tests/test_start.py
tests/test_stop.py
tests/test_undeploy.py
tests/test_unit.py
tests/test_verify.py
roe-1.0.3.dist-info/LICENSE
roe-1.0.3.dist-info/METADATA
roe-1.0.3.dist-info/WHEEL
roe-1.0.3.dist-info/entry_points.txt
roe-1.0.3.dist-info/top_level.txt
roe-1.0.3.dist-info/RECORD
