Metadata-Version: 2.1
Name: roe
Version: 1.0.3
Summary: This utility helps you deploy your code as an API locally on your machine
Home-page: https://github.com/pypa/roe
Author: Chainopt
Author-email: support@chainopt.com
License: Apache License Version 2.0
Project-URL: Bug Tracker, https://github.com/chainopt/roe-cli/issues
Keywords: Swagger,OpenAPI,ModelOps,CLI,DataScience
Platform: UNKNOWN
Classifier: Topic :: Utilities
Classifier: Intended Audience :: Developers
Classifier: Intended Audience :: End Users/Desktop
Classifier: Intended Audience :: Information Technology
Classifier: Intended Audience :: Science/Research
Classifier: License :: OSI Approved :: Apache Software License
Classifier: Operating System :: OS Independent
Classifier: Programming Language :: Python
Classifier: Programming Language :: Python :: 3
Classifier: Programming Language :: Python :: 3.6
Classifier: Programming Language :: Python :: 3.7
Classifier: Programming Language :: Python :: 3.8
Classifier: Programming Language :: Python :: 3.9
License-File: LICENSE
Requires-Dist: click (==7.1.2)
Requires-Dist: docker (==5.0.0)
Requires-Dist: keyring (==23.0.1)
Requires-Dist: numpy (==1.20.1)
Requires-Dist: pandas (==1.2.3)
Requires-Dist: PyYAML (==5.4.1)
Requires-Dist: requests (==2.25.1)
Requires-Dist: stdiomask (==0.0.6)
Requires-Dist: setuptools
